soorgeon/__init__.py
soorgeon/_debug.py
soorgeon/_kaggle.py
soorgeon/_pygithub.py
soorgeon/clean.py
soorgeon/cli.py
soorgeon/definitions.py
soorgeon/detect.py
soorgeon/exceptions.py
soorgeon/export.py
soorgeon/get.py
soorgeon/io.py
soorgeon/magics.py
soorgeon/proto.py
soorgeon/pyflakes.py
soorgeon/split.py
soorgeon/assets/README.md
soorgeon/assets/__init__.py
soorgeon-0.0.20.dist-info/LICENSE
soorgeon-0.0.20.dist-info/METADATA
soorgeon-0.0.20.dist-info/WHEEL
soorgeon-0.0.20.dist-info/entry_points.txt
soorgeon-0.0.20.dist-info/top_level.txt
soorgeon-0.0.20.dist-info/RECORD
