Metadata-Version: 2.1
Name: soorgeon
Version: 0.0.20
Summary: Convert monolithic Jupyter notebooks into maintainable pipelines.
Home-page: https://github.com/ploomber/soorgeon
Author: Eduardo Blancas
Author-email: hello@ploomber.io
License-File: LICENSE
Requires-Dist: ploomber-core (>=0.0.4)
Requires-Dist: jupytext
Requires-Dist: parso
Requires-Dist: nbformat
Requires-Dist: jinja2
Requires-Dist: pyyaml
Requires-Dist: click
Requires-Dist: isort
Requires-Dist: pyflakes
Requires-Dist: black[jupyter] (>=22.6.0)
Requires-Dist: papermill
Provides-Extra: dev
Requires-Dist: pkgmt ; extra == 'dev'
Requires-Dist: pytest ; extra == 'dev'
Requires-Dist: yapf ; extra == 'dev'
Requires-Dist: flake8 ; extra == 'dev'
Requires-Dist: invoke ; extra == 'dev'
Requires-Dist: twine ; extra == 'dev'
Requires-Dist: ipython ; extra == 'dev'
Requires-Dist: ploomber ; extra == 'dev'
Requires-Dist: kaggle ; extra == 'dev'
Requires-Dist: pygithub ; extra == 'dev'
Requires-Dist: pandas ; extra == 'dev'
Requires-Dist: scikit-learn ; extra == 'dev'
Requires-Dist: seaborn ; extra == 'dev'
